jupyspace_api/__init__.py
jupyspace_api/app.py
jupyspace_api/cli.py
jupyspace_api/exceptions.py
jupyspace_api/main.py
jupyspace_api/router.py
jupyspace_api/space/__init__.py
jupyspace_api/space/models.py
jupyspace_api-0.0.4.dist-info/METADATA
jupyspace_api-0.0.4.dist-info/WHEEL
jupyspace_api-0.0.4.dist-info/entry_points.txt
jupyspace_api-0.0.4.dist-info/licenses/LICENSE.txt
jupyspace_api-0.0.4.dist-info/RECORD
